partition.v
module partition(i,j,loc_in,clk,init,complete);
parameter N = 8;
input clk,init;
reg[31:0] vec[0:N-1];
input[31:0] i,j;
input[31:0] loc_in;
output reg complete;
reg[31:0] right,left,loc;
reg set;
reg[31:0] temp;
reg[3:0] state;
parameter S0=4'b0000,S1=4'b0001,S2=4'b0010,S3=4'b0011,S4=4'b0100,S5=4'b0101,S6=4'b0110,S7=4'b0111,S8=4'b1000;
// always @(posedge init) begin
//     state<=S0;
//     set<=0;
//     loc<=loc_in;
//     complete<=0;
//     left<=i;
//     right<=j;
// end
always @(posedge clk) begin
    case(state)
    S0:begin state<=set?S0:S1; complete<=0;loc<=loc_in;complete<=0;left<=i;right<=j;end
    S1:begin
      complete<=0;
      if(vec[loc]<=vec[right] && loc!=right)state<=S2;
      else if(vec[loc]>vec[right])begin state<=S4;vec[loc]<=vec[right];vec[right]<=vec[loc];loc<=right;end
      else if(loc==right)state<=S3;
    end
    S2:begin
      if(vec[loc]<=vec[right] && loc!=right)begin state<=S2;right<=right-1;end
      else if(vec[loc]>vec[right])begin state<=S4;vec[loc]<=vec[right];vec[right]<=vec[loc];loc<=right;end
      else if(loc==right)state<=S3;
    end
    S3:begin state<=S0;set<=1;end
    S4:begin
      if(vec[loc]>=vec[left] && left!=loc)state<=S5;
      else if(vec[loc]<vec[left])begin state<=S7;vec[loc]<=vec[left];vec[left]<=vec[loc];loc<=left; end
      else if(loc==left)state<=S6;
    end
    S5:begin
      if(vec[loc]>=vec[left] && left!=loc)begin state<=S5;left<=left+1; end
      else if(vec[loc]<vec[left])begin state<=S7;vec[loc]<=vec[left];vec[left]<=vec[loc];loc<=left; end
      else if(loc==left)state<=S6;
    end
    S6:begin state<=init?S0:S6;set<=1;complete<=1; end
    S7:state<=S1;
    endcase
end
endmodule

partition_test.v
module partition_test;
parameter N = 8;
reg clk,init;
reg[31:0] i,j;
reg[31:0] loc_in;
integer c;
wire complete;
partition DUT(i,j,loc_in,clk,init,complete);
initial begin
    clk=0;
    init=0;
    DUT.state=4'b0000;
    DUT.set=0;
    DUT.vec[0]=13;DUT.vec[1]=2;DUT.vec[2]=8;DUT.vec[3]=12;DUT.vec[4]=1;DUT.vec[5]=3;DUT.vec[6]=31;DUT.vec[7]=22;
    i=0;
    j=N-1;
    loc_in=0;
    for(c=0;c<N;c=c+1)begin
      $write("%0d ",DUT.vec[c]);
    end
    $write("\n");
    #2 init=1;
    #500 $finish;
end
always #5 clk=~clk;
always @(posedge complete) begin
    for(c=0;c<N;c=c+1)begin
      $write("%0d ",DUT.vec[c]);
    end
    $write("\n");
end
initial begin
    $dumpfile("partition_test.vcd");
    $dumpvars(0,partition_test);
end
endmodule

partition_test.vcd
$date
	Tue Apr 12 10:31:22 2022
$end
$version
	Icarus Verilog
$end
$timescale
	1s
$end
$scope module partition_test $end
$var wire 1 ! complete $end
$var reg 1 " clk $end
$var reg 32 # i [31:0] $end
$var reg 1 $ init $end
$var reg 32 % j [31:0] $end
$var reg 32 & loc_in [31:0] $end
$var integer 32 ' c [31:0] $end
$scope module DUT $end
$var wire 1 " clk $end
$var wire 32 ( i [31:0] $end
$var wire 1 $ init $end
$var wire 32 ) j [31:0] $end
$var wire 32 * loc_in [31:0] $end
$var reg 1 ! complete $end
$var reg 32 + left [31:0] $end
$var reg 32 , loc [31:0] $end
$var reg 32 - right [31:0] $end
$var reg 1 . set $end
$var reg 4 / state [3:0] $end
$upscope $end
$upscope $end
$enddefinitions $end
#0
$dumpvars
b0 /
0.
bx -
bx ,
bx +
b0 *
b111 )
b0 (
b1000 '
b0 &
b111 %
0$
b0 #
0"
x!
$end
#2
1$
#5
b111 -
b0 +
b0 ,
0!
b1 /
1"
#10
0"
#15
b10 /
1"
#20
0"
#25
b110 -
1"
#30
0"
#35
b101 -
1"
#40
0"
#45
b101 ,
b100 /
1"
#50
0"
#55
b101 /
1"
#60
0"
#65
b1 +
1"
#70
0"
#75
b10 +
1"
#80
0"
#85
b11 +
1"
#90
0"
#95
b100 +
1"
#100
0"
#105
b101 +
1"
#110
0"
#115
b110 /
1"
#120
0"
#125
b1000 '
1!
1.
b0 /
1"
#130
0"
#135
b111 -
b0 +
b0 ,
0!
1"
